<?xml version="1.0" encoding="UTF-8"?>
<xtce:SpaceSystem name="AcubeSAT" xmlns:xtce="http://www.omg.org/spec/XTCE/20180204" xmlns:xsi="http://www.w3.org/2001/XMLSchema-instance" xsi:schemaLocation="http://www.omg.org/spec/XTCE/20180204 https://www.omg.org/spec/XTCE/20180204/SpaceSystem.xsd" shortDescription="This is a bogus satellite telemetry and telecommand database." operationalStatus="unittest">

<!--Contains all Parameters that will be used in the Environmental Campaign-->
    <xtce:TelemetryMetaData>
        <xtce:ParameterSet> 
            <!--*OBC Parameters that will be used in the Enviromental Campaign-->
            <xtce:Parameter parameterTypeRef="/dt/uint16_t" name="reportParametersUnusedStack"></xtce:Parameter>    
            <xtce:Parameter parameterTypeRef="/dt/uint16_t" name="availableHeap"></xtce:Parameter>
            <xtce:Parameter parameterTypeRef="/dt/bool_t" name="obcUseRTT"></xtce:Parameter>    
            <xtce:Parameter parameterTypeRef="/dt/bool_t" name="obcUseUART"></xtce:Parameter>    
            <xtce:Parameter parameterTypeRef="/dt/bool_t" name="obcUseCAN"></xtce:Parameter>    
            <xtce:Parameter parameterTypeRef="/dt/bool_t" name="adcsUseRTT"></xtce:Parameter>    
            <xtce:Parameter parameterTypeRef="/dt/bool_t" name="adcsUseUART"></xtce:Parameter>    
            <xtce:Parameter parameterTypeRef="/dt/bool_t" name="adcsUseCAN"></xtce:Parameter>    
            <xtce:Parameter parameterTypeRef="/dt/uint32_t" name="onBoardTime"></xtce:Parameter>
            <xtce:Parameter parameterTypeRef="/dt/uint16_t" name="obcBootCounter"></xtce:Parameter>    
            <xtce:Parameter parameterTypeRef="/dt/uint64_t" name="obcSysTick"></xtce:Parameter>    
            <xtce:Parameter parameterTypeRef="/dt/float_t" name="mcuTemperature"></xtce:Parameter>    
            <xtce:Parameter parameterTypeRef="/dt/float_t" name="obcMCUTemperature"></xtce:Parameter>   
            <xtce:Parameter parameterTypeRef="/dt/float_t" name="obdhBoardTemperature1"></xtce:Parameter>   
            <xtce:Parameter parameterTypeRef="/dt/float_t" name="obdhBoardTemperature2"></xtce:Parameter>
            <xtce:Parameter parameterTypeRef="/dt/uint32_t" name="obcMCUSysTick"></xtce:Parameter>
            <xtce:Parameter parameterTypeRef="/dt/uint32_t" name="obcOnBoardTime"></xtce:Parameter>
            <xtce:Parameter parameterTypeRef="/dt/float_t" name="CANbus1Load"></xtce:Parameter>
            <xtce:Parameter parameterTypeRef="/dt/float_t" name="CANbus2Load"></xtce:Parameter>
            <xtce:Parameter parameterTypeRef="/dt/float_t" name="obcNANDFLASHLCLThreshold"></xtce:Parameter>
            <xtce:Parameter parameterTypeRef="/dt/float_t" name="obcMRAMLCLThreshold"></xtce:Parameter>
            <xtce:Parameter parameterTypeRef="/dt/float_t" name="obcNANDFLASHON"></xtce:Parameter>
            <xtce:Parameter parameterTypeRef="/dt/float_t" name="obcMRAMON"></xtce:Parameter>
            <xtce:Parameter parameterTypeRef="/dt/uint8_t" name="obcNANDCurrentlyUsedMemoryPartition"></xtce:Parameter>
            <xtce:Parameter parameterTypeRef="/dt/bool_t" name="activeCAN"></xtce:Parameter>
            <!--* ADCS Parameters that will be used in the Enviromental Campaign-->
            <xtce:Parameter parameterTypeRef="/dt/uint8_t" name="magnetometerRawX"></xtce:Parameter>
            <xtce:Parameter parameterTypeRef="/dt/uint8_t" name="magnetometerRawY"></xtce:Parameter> 
            <xtce:Parameter parameterTypeRef="/dt/uint8_t" name="magnetometerRawZ"></xtce:Parameter> 
            <xtce:Parameter parameterTypeRef="/dt/uint8_t" name="magnetometerFrequency"></xtce:Parameter> 
            <xtce:Parameter parameterTypeRef="/dt/int8_t" name="magnetometerCycleCountX"></xtce:Parameter> 
            <xtce:Parameter parameterTypeRef="/dt/int8_t" name="magnetometerCycleCountY"></xtce:Parameter> 
            <xtce:Parameter parameterTypeRef="/dt/int8_t" name="magnetometerCycleCountZ"></xtce:Parameter>     
            <xtce:Parameter parameterTypeRef="/dt/bool_t" name="magnetometerSelfTest"></xtce:Parameter>
            <xtce:Parameter parameterTypeRef="/dt/uint32_t" name="gyroscopeX"></xtce:Parameter>
            <xtce:Parameter parameterTypeRef="/dt/uint32_t" name="gyroscopeY"></xtce:Parameter>
            <xtce:Parameter parameterTypeRef="/dt/uint32_t" name="gyroscopeZ"></xtce:Parameter>
            <xtce:Parameter parameterTypeRef="/dt/bool_t" name="magnetometerSignX"></xtce:Parameter>
            <xtce:Parameter parameterTypeRef="/dt/bool_t" name="magnetometerSignY"></xtce:Parameter> 
            <xtce:Parameter parameterTypeRef="/dt/bool_t" name="magnetometerSignZ"></xtce:Parameter> 
            <xtce:Parameter parameterTypeRef="/dt/uint32_t" name="gyroscopeXTemperature"></xtce:Parameter>
            <xtce:Parameter parameterTypeRef="/dt/uint32_t" name="gyroscopeYTemperature"></xtce:Parameter>
            <xtce:Parameter parameterTypeRef="/dt/uint32_t" name="gyroscopeZTemperature"></xtce:Parameter>
            <xtce:Parameter parameterTypeRef="/dt/uint32_t" name="adcsBoardTemperature1"></xtce:Parameter>
            <xtce:Parameter parameterTypeRef="/dt/uint32_t" name="adcsBoardTemperature2"></xtce:Parameter>
            <xtce:Parameter parameterTypeRef="/dt/bool_t" name="gyroSignX"></xtce:Parameter>
            <xtce:Parameter parameterTypeRef="/dt/bool_t" name="gyroSignY"></xtce:Parameter>
            <xtce:Parameter parameterTypeRef="/dt/bool_t" name="gyroSignZ"></xtce:Parameter>
            <xtce:Parameter parameterTypeRef="/dt/bool_t" name="gyroBiasX"></xtce:Parameter>
            <xtce:Parameter parameterTypeRef="/dt/bool_t" name="gyroBiasY"></xtce:Parameter>
            <xtce:Parameter parameterTypeRef="/dt/bool_t" name="gyroBiasZ"></xtce:Parameter>
            <xtce:Parameter parameterTypeRef="/dt/float_t" name="adcsMCUTemperature"></xtce:Parameter>
            <xtce:Parameter parameterTypeRef="/dt/float_t" name="adcsMCUOnBoardTime"></xtce:Parameter>
            <xtce:Parameter parameterTypeRef="/dt/uint64_t" name="adcsSystick"></xtce:Parameter>
            <xtce:Parameter parameterTypeRef="/dt/uint16_t" name="adcsBootCounter"></xtce:Parameter>
        </xtce:ParameterSet>
    </xtce:TelemetryMetaData>

</xtce:SpaceSystem>
